{"noiseKey":{"private":{"type":"Buffer","data":"+MdeYnPRWFDbUkSO/dFgRBWoHKh4UBFd6J52+Tc5CVc="},"public":{"type":"Buffer","data":"2yoKaimC0V8pIj1XT3QfiwtcSS5eBzfEJsEgRN5hLnw="}},"pairingEphemeralKeyPair":{"private":{"type":"Buffer","data":"2IevH7Z6bZOSm5VHGPEvf9r+9N3mLgdedTtkI4KOTlY="},"public":{"type":"Buffer","data":"DjIC5BdrrHi19QcaYyFRiR+bG/xxKDF0S09JjRpY8V4="}},"signedIdentityKey":{"private":{"type":"Buffer","data":"uM1jZ8rh++/c6QwDS0TU7WLqBezwXLwO5rAOeL3tOWE="},"public":{"type":"Buffer","data":"1hkzPzJtRzNgLFzam/iRagZ6fwnZtw2FqYS+DY18EjI="}},"signedPreKey":{"keyPair":{"private":{"type":"Buffer","data":"+NlkPFWrvIqDlkUNfkCrkMWOjk6VfWBGuJwNx65hNXU="},"public":{"type":"Buffer","data":"iw7BWRiLUEeUWi/a+AxwDPlcFIsbUa5Ano42z5tp8X0="}},"signature":{"type":"Buffer","data":"vPf2+FOGzuxXuB6HF2uePjnT7riziPx+SxeE15tlt8D9moGaCup/3f27/I4ecpnKKBfcBOFs0mp4al6eg5kbDQ=="},"keyId":1},"registrationId":206,"advSecretKey":"jOcHPsNGxCc0+fph3xJ53B0ADO6HN6eSlpqeDSS8iJo=","processedHistoryMessages":[{"key":{"remoteJid":"918107171472@s.whatsapp.net","fromMe":false,"id":"ACF4C1F48FBF373548E13FB51F946B8B","participant":"","addressingMode":"pn"},"messageTimestamp":1764593509},{"key":{"remoteJid":"918107171472@s.whatsapp.net","fromMe":false,"id":"AC6FFFDF6E04ED33066237EF816A6F47","participant":"","addressingMode":"pn"},"messageTimestamp":1764593509},{"key":{"remoteJid":"918107171472@s.whatsapp.net","fromMe":false,"id":"AC17A227181823E5961D4289A511DAFC","participant":"","addressingMode":"pn"},"messageTimestamp":1764593509},{"key":{"remoteJid":"918107171472@s.whatsapp.net","fromMe":false,"id":"AC956464205765B6EBB7E1F0BDB4A699","participant":"","addressingMode":"pn"},"messageTimestamp":1764593509},{"key":{"remoteJid":"918107171472@s.whatsapp.net","fromMe":false,"id":"ACE8F10029FB2DFEAA5350086F5F6B4D","participant":"","addressingMode":"pn"},"messageTimestamp":1764593527},{"key":{"remoteJid":"918107171472@s.whatsapp.net","fromMe":false,"id":"ACB268C9EE6EF2AD563BC4B99E7567CB","participant":"","addressingMode":"pn"},"messageTimestamp":1764593529},{"key":{"remoteJid":"918107171472@s.whatsapp.net","fromMe":false,"id":"ACAC867E84004DA6CBC78B8F38A1B33C","participant":"","addressingMode":"pn"},"messageTimestamp":1764593597},{"key":{"remoteJid":"918107171472@s.whatsapp.net","fromMe":false,"id":"AC88C53079EFB815525AEA26EC285564","participant":"","addressingMode":"pn"},"messageTimestamp":1764593605},{"key":{"remoteJid":"918107171472@s.whatsapp.net","fromMe":false,"id":"AC85C1F712BCAFF98523264C233EE8CA","participant":"","addressingMode":"pn"},"messageTimestamp":1764593612},{"key":{"remoteJid":"918107171472@s.whatsapp.net","fromMe":false,"id":"AC5B47B7A59E6FDDDB1D5AD37D257DB8","participant":"","addressingMode":"pn"},"messageTimestamp":1764593612},{"key":{"remoteJid":"918107171472@s.whatsapp.net","fromMe":false,"id":"ACAE045C1DE8EC6EFE59D8F52E5F0511","participant":"","addressingMode":"pn"},"messageTimestamp":1764593613},{"key":{"remoteJid":"918107171472@s.whatsapp.net","fromMe":false,"id":"AC9A7AC754E51C961B74AA2874CE23A1","participant":"","addressingMode":"pn"},"messageTimestamp":1764593615},{"key":{"remoteJid":"918107171472@s.whatsapp.net","fromMe":false,"id":"AC7F86815685D80131F1CA33AFAE1F7A","participant":"","addressingMode":"pn"},"messageTimestamp":1764593621}],"nextPreKeyId":1655,"firstUnuploadedPreKeyId":1655,"accountSyncCounter":2,"accountSettings":{"unarchiveChats":false},"registered":false,"account":{"details":"CMnJ884BENaetskGGBEgACgA","accountSignatureKey":"pq6oOfgihiXodhSF0U4i9Jo7rpA3wtsUBXFUDXm+ckM=","accountSignature":"d4DnIvTM4e6lQITg95TIyhmo4Zhs11/85UrTsd2emoSI0TAjHjj9yiBhCoJucNmBhKYDlPxPMJOWqKiDC6stAw==","deviceSignature":"HjqwFd80LidmSIkJW7eUpySHKl0QLfeSSticd9f4Qn0dNmtwThYabEpWnuRdLMTP6HQfxoK2Ze2KUAraH0c7DA=="},"me":{"id":"918107171472:92@s.whatsapp.net","lid":"122758822375543:92@lid","name":"yd"},"signalIdentities":[{"identifier":{"name":"122758822375543:92@lid","deviceId":0},"identifierKey":{"type":"Buffer","data":"BaauqDn4IoYl6HYUhdFOIvSaO66QN8LbFAVxVA15vnJD"}}],"platform":"android","routingInfo":{"type":"Buffer","data":"CBIIAggN"},"lastAccountSyncTimestamp":1764593506,"lastPropHash":"C4fJN","myAppStateKeyId":"AAAAAEoC"}